LICENSE
setup.py
toremath/__init__.py
toremath/__version__.py
toremath/activation.py
toremath/analysis.py
toremath/builtins.py
toremath/check.py
toremath/clibs.py
toremath/combinatorial.py
toremath/consts.py
toremath/errs_from_check.py
toremath/exponential.py
toremath/function.py
toremath/generalized.py
toremath/generictypes.py
toremath/logarithm.py
toremath/special.py
toremath/toremath.py
toremath/trig.py
toremath.egg-info/PKG-INFO
toremath.egg-info/SOURCES.txt
toremath.egg-info/dependency_links.txt
toremath.egg-info/requires.txt
toremath.egg-info/top_level.txt